setup.py
dm/__init__.py
dm.xmlsec.pyxb.egg-info/PKG-INFO
dm.xmlsec.pyxb.egg-info/SOURCES.txt
dm.xmlsec.pyxb.egg-info/dependency_links.txt
dm.xmlsec.pyxb.egg-info/namespace_packages.txt
dm.xmlsec.pyxb.egg-info/not-zip-safe
dm.xmlsec.pyxb.egg-info/requires.txt
dm.xmlsec.pyxb.egg-info/top_level.txt
dm/xmlsec/__init__.py
dm/xmlsec/pyxb/LICENSE.txt
dm/xmlsec/pyxb/README.txt
dm/xmlsec/pyxb/VERSION.txt
dm/xmlsec/pyxb/__init__.py
dm/xmlsec/pyxb/dsig.py
dm/xmlsec/pyxb/enc.py
dm/xmlsec/pyxb/util.py