Metadata-Version: 1.0
Name: dm.xmlsec.pyxb
Version: 1.1
Summary: Tiny wrapper around the 'wssplat' bundle of 'pyxb' for XML-Signature and XML-Encryption -- obsolete.
Home-page: http://pypi.python.org/pypi/dm.xmlsec.pyxb
Author: Dieter Maurer
Author-email: dieter@handshake.de
License: BSD
Keywords: pyxb xml security digital signature
Platform: UNKNOWN
Classifier: Development Status :: 5 - Production/Stable
Classifier: Intended Audience :: Developers
Classifier: License :: OSI Approved :: BSD License
Classifier: Operating System :: OS Independent
Classifier: Programming Language :: Python :: 2.4
Classifier: Programming Language :: Python :: 2.6
Classifier: Topic :: Utilities
